py2md/__init__.py
py2md/__main__.py
py2md/jupyter.py
py2md/py2md.py
py2md/classes/__init__.py
py2md/classes/mdfigure.py
py2md/classes/mdheading.py
py2md/classes/mdlist.py
py2md/classes/mdmatrix.py
py2md/classes/mdobject.py
py2md/classes/mdparamlist.py
py2md/classes/mdparamtable.py
py2md/classes/mdreport.py
py2md/classes/mdstring.py
py2md/classes/mdtable.py
py2md/output/__init__.py
py2md/output/md.py
py2md-0.1.3.dist-info/licenses/LICENSE
py2md-0.1.3.dist-info/METADATA
py2md-0.1.3.dist-info/WHEEL
py2md-0.1.3.dist-info/entry_points.txt
py2md-0.1.3.dist-info/top_level.txt
py2md-0.1.3.dist-info/RECORD
