Metadata-Version: 2.4
Name: py2md
Version: 0.1.3
Summary: Run Python code in Jupyter to generate markdown reports.
Author-email: Xero64 <xero64@gmail.com>
License-Expression: MIT
Project-URL: Homepage, https://github.com/Xero64/py2md
Project-URL: Issues, https://github.com/Xero64/py2md/issues
Classifier: Programming Language :: Python :: 3
Classifier: Operating System :: OS Independent
Requires-Python: >=3.10
License-File: LICENSE
Requires-Dist: jupyter-client>=8.6.3
Requires-Dist: matplotlib>=3.10.0
Requires-Dist: nbformat>=5.10.4
Dynamic: license-file
